CMakeLists.txt
CODE_OF_CONDUCT.md
LICENSE
MANIFEST.in
README.rst
pyproject.toml
setup.cfg
setup.py
_custom_build/backend.py
docs/Makefile
docs/make.bat
docs/source/api.rst
docs/source/changelog.rst
docs/source/conf.py
docs/source/core_api.rst
docs/source/index.rst
docs/source/setup.rst
docs/source/_static/pyinterp-dark.svg
docs/source/_static/pyinterp-light.svg
docs/source/_templates/autosummary/base.rst
docs/source/_templates/autosummary/class.rst
docs/source/_templates/autosummary/module.rst
docs/source/pictures/binning_2d.svg
docs/source/pictures/coordinates.svg
docs/source/pictures/mit_gcm.png
docs/source/pictures/time_series.png
docs/source/setup/build.rst
docs/source/setup/conda.rst
docs/source/setup/pip.rst
src/pyinterp/__init__.py
src/pyinterp/_geohash.py
src/pyinterp/binning.py
src/pyinterp/cf.py
src/pyinterp/conftest.py
src/pyinterp/fill.py
src/pyinterp/grid.py
src/pyinterp/histogram2d.py
src/pyinterp/interface.py
src/pyinterp/orbit.py
src/pyinterp/period.py
src/pyinterp/rtree.py
src/pyinterp/typing.py
src/pyinterp/version.py
src/pyinterp.egg-info/PKG-INFO
src/pyinterp.egg-info/SOURCES.txt
src/pyinterp.egg-info/dependency_links.txt
src/pyinterp.egg-info/not-zip-safe
src/pyinterp.egg-info/requires.txt
src/pyinterp.egg-info/top_level.txt
src/pyinterp/backends/__init__.py
src/pyinterp/backends/xarray.py
src/pyinterp/core/CMakeLists.txt
src/pyinterp/core/__init__.pyi
src/pyinterp/core/array.pyi
src/pyinterp/core/dateutils.pyi
src/pyinterp/core/fill.pyi
src/pyinterp/core/geodetic.pyi
src/pyinterp/core/geohash/__init__.pyi
src/pyinterp/core/geohash/int64.pyi
src/pyinterp/core/include/pyinterp/axis.hpp
src/pyinterp/core/include/pyinterp/binning.hpp
src/pyinterp/core/include/pyinterp/bivariate.hpp
src/pyinterp/core/include/pyinterp/dateutils.hpp
src/pyinterp/core/include/pyinterp/descriptive_statistics.hpp
src/pyinterp/core/include/pyinterp/eigen.hpp
src/pyinterp/core/include/pyinterp/fill.hpp
src/pyinterp/core/include/pyinterp/frame.hpp
src/pyinterp/core/include/pyinterp/geohash.hpp
src/pyinterp/core/include/pyinterp/grid.hpp
src/pyinterp/core/include/pyinterp/histogram2d.hpp
src/pyinterp/core/include/pyinterp/interpolate1d.hpp
