Metadata-Version: 2.4
Name: pyinterp
Version: 2025.8.1
Summary: Interpolation of geo-referenced data for Python.
Home-page: https://github.com/CNES/pangeo-pyinterp
Author: CNES/CLS
Author-email: fbriol@gmail.com
License: BSD-3-Clause
Keywords: interpolation,geospatial,geohash,geodetic
Platform: POSIX
Platform: MacOS
Platform: Windows
Classifier: Development Status :: 5 - Production/Stable
Classifier: Topic :: Scientific/Engineering :: Physics
Classifier: Natural Language :: English
Classifier: Operating System :: POSIX
Classifier: Operating System :: MacOS
Classifier: Operating System :: Microsoft :: Windows
Classifier: Programming Language :: Python :: 3.10
Classifier: Programming Language :: Python :: 3.11
Classifier: Programming Language :: Python :: 3.12
Classifier: Programming Language :: Python :: 3.13
Requires-Python: >=3.10
License-File: LICENSE
Requires-Dist: dask
Requires-Dist: numpy
Requires-Dist: xarray>=0.13
Dynamic: author
Dynamic: author-email
Dynamic: classifier
Dynamic: description
Dynamic: description-content-type
Dynamic: home-page
Dynamic: keywords
Dynamic: license
Dynamic: license-file
Dynamic: platform
Dynamic: requires-dist
Dynamic: requires-python
Dynamic: summary
